{
  "liste": [
    {
      "nom": "Magasin Paris Bercy Village",
      "adresse": "Place du 11 novembre 1918 Gare de L'Est, 75010 Paris",
      "horaire" : "Horaires d'ouverture : 7h - 21h",
      "tel" : "04.93.77.09.23",
      "email" : "client@tobeortohave.com"
    },
    {
      "nom": "Magasin Paris Forum des Halles",
      "adresse": "25 Avenue de la République, 75010 Paris",
      "horaire" : "Horaires d'ouverture : 8h - 20h",
      "tel" : "04.78.65.21.50",
      "email" : "client@tobeortohave.com"
    },
    {
      "nom": "Magasin Paris Montparnasse",
      "adresse": "Place du grand pont, 75010 Paris",
      "horaire" : "Horaires d'ouverture : 8h - 19h30h",
      "tel" : "04.58.95.32.14",
      "email" : "client@tobeortohave.com"
    },
    {
      "nom": "Magasin Paris Champ Elysées",
      "adresse": "48 Place du palais, 75010 Paris",
      "horaire" : "Horaires d'ouverture : 8h - 12h",
      "tel" : "04.92.58.42.19",
      "email" : "client@tobeortohave.com"
    },
    {
      "nom": "Magasin Paris Ouest",
      "adresse": "Place du 11 novembre 1918 Gare de L'Est, 75010 Paris",
      "horaire" : "Horaires d'ouverture : 7h - 21h",
      "tel" : "04.93.77.09.22",
      "email" : "client@tobeortohave.com"
    },
    {
      "nom": "Magasin Paris Saint Lazare",
      "adresse": "25 Avenue de la République, 75010 Paris",
      "horaire" : "Horaires d'ouverture : 8h - 21h",
      "tel" : "04.78.65.21.50",
      "email" : "client@tobeortohave.com"
    },
    {
      "nom": "Magasin Paris Gare de l'Est",
      "adresse": "Place du grand pont, 75010 Paris",
      "horaire" : "Horaires d'ouverture : 8h - 19h30h",
      "tel" : "04.58.95.32.14",
      "email" : "client@tobeortohave.com"
    },
    {
      "nom": "Magasin Paris Gare Montparnasse",
      "adresse": "48 Place du palais, 75010 Paris",
      "horaire" : "Horaires d'ouverture : 8h - 12h",
      "tel" : "04.92.58.42.10",
      "email" : "client@tobeortohave.com"
    },
    {
      "nom": "Magasin Paris Gare de Lyon",
      "adresse": "48 Place du palais, 75010 Paris",
      "horaire" : "Horaires d'ouverture : Fermé",
      "tel" : "04.92.58.42.10",
      "email" : "client@tobeortohave.com"
    }]
}